basiclog/__init__.py
basiclog-0.1.1.dist-info/WHEEL
basiclog-0.1.1.dist-info/METADATA
basiclog-0.1.1.dist-info/RECORD
