Metadata-Version: 2.1
Name: basiclog
Version: 0.1.1
Summary: 
License: MIT
Author: Ramon Brandt
Author-email: devramon22@gmail.com
Requires-Python: >=3.6,<4.0
Classifier: License :: OSI Approved :: MIT License
Classifier: Programming Language :: Python :: 3
Classifier: Programming Language :: Python :: 3.6
Classifier: Programming Language :: Python :: 3.7
Classifier: Programming Language :: Python :: 3.8
Requires-Dist: slackclient (>=2.5.0,<3.0.0)
